src/__init__.py
src/demo/__init__.py
src/demo/main.py
python_pkg_builder_2-0.0.1.dist-info/entry_points.txt
python_pkg_builder_2-0.0.1.dist-info/LICENSE
python_pkg_builder_2-0.0.1.dist-info/WHEEL
python_pkg_builder_2-0.0.1.dist-info/METADATA
python_pkg_builder_2-0.0.1.dist-info/RECORD
