Metadata-Version: 2.1
Name: python_pkg_builder_2
Version: 0.0.1
Summary: init file
Author: preetam verma
